obliquestrategies/__init__.py
obliquestrategies/obliquestrategies.py
obliquestrategies/resources/edition_1_1975.txt
obliquestrategies/resources/edition_2_1978.txt
obliquestrategies/resources/edition_3_1979.txt
obliquestrategies/resources/edition_4_1996.txt
obliquestrategies-0.3.data/scripts/obliquestrategies
obliquestrategies-0.3.dist-info/METADATA
obliquestrategies-0.3.dist-info/RECORD
obliquestrategies-0.3.dist-info/WHEEL
obliquestrategies-0.3.dist-info/top_level.txt
