Metadata-Version: 2.1
Name: obliquestrategies
Version: 0.3
Summary: Over One Hundred Worthwhile Dilemmas
Home-page: https://github.com/FdelMazo/obliquestrategies
Author: FdelMazo
Author-email: UNKNOWN
License: UNKNOWN
Platform: UNKNOWN
Classifier: Programming Language :: Python :: 2
Classifier: Programming Language :: Python :: 3
